bsimage2pdf/__init__.py
bsimage2pdf/image2pdf.py
bsimage2pdf-0.0.17.dist-info/licenses/LICENSE
bsimage2pdf-0.0.17.dist-info/METADATA
bsimage2pdf-0.0.17.dist-info/WHEEL
bsimage2pdf-0.0.17.dist-info/top_level.txt
bsimage2pdf-0.0.17.dist-info/RECORD
