Metadata-Version: 2.4
Name: bsimage2pdf
Version: 0.0.17
Summary: 冰鼠图片转成Pdf文件
Author: bs
License-File: LICENSE
Requires-Dist: PyMuPDF==1.26.4
Dynamic: author
Dynamic: license-file
Dynamic: requires-dist
Dynamic: summary
